bothpy_jees/__init__.py
bothpy_jees/api/__init__.py
bothpy_jees/api/jees_constant.py
bothpy_jees/api/thosttraderapi_se.dll
bothpy_jees/api/vnjeestd.cp310-win_amd64.pyd
bothpy_jees/api/vnjees/vnjeestd/vnjeestd.cpp
bothpy_jees/gateway/__init__.py
bothpy_jees/gateway/jees_gateway.py
bothpy_jees-6.6.1.2.dist-info/LICENSE
bothpy_jees-6.6.1.2.dist-info/METADATA
bothpy_jees-6.6.1.2.dist-info/WHEEL
bothpy_jees-6.6.1.2.dist-info/top_level.txt
bothpy_jees-6.6.1.2.dist-info/RECORD
